[
   
    {
        "Qualification": "Bachelor of Environmental Sciences",
        "Qualification Code": "ESBBES",
        "ID": 988,
        "APS": 32,
        "Subject": [
            {"English": 50},
            {"Mathematics": 40},
            {"Physical Sciences": 40},
            {"Life Sciences": 50},
            {"Geography": 50},
            {"Agriculture": 50}

        ],
        "Duration": "3 years"
    },
    {
        "Qualification": "Bachelor of Earth Sciences in Mining and Environmental Geology",
        "Qualification Code": "ESBMEG",
        "ID": 990,
        "APS": 35,
        "Subject": [
            {"English": 50},
            {"Mathematics": 60},
            {"Physical Sciences": 50},
            {"Agricultural Sciences": 50},
            {"Accounting": 50},
            {"Life Sciences": 50},
            {"Economics": 50},
            {"Geography": 50}
        ],
        "Duration": "4 years"
    },
    {
        "Qualification": "Bachelor of Earth Sciences in Hydrology and Water Resources",
        "Qualification Code": "ESBHWR",
        "ID": 977,
        "APS": 35,
        "Subject": [
            {"English": 60},
            {"Mathematics": 60},
            {"Physical Sciences": 60},
            {"Agricultural Sciences": 50},
            {"Accounting": 50},
            {"Life Sciences": 50},
            {"Economics": 50},
            {"Geography": 50}
        ],
        "Duration": "4 years"
    },
    {
        "Qualification": "Bachelor of Urban and Regional Planning",
        "Qualification Code": "ESBURP",
        "ID": 989,
        "APS": 35,
        "Subject": [
            {"English": 50},
            {"Mathematics": 50},
            {"Physical Sciences": 60},
            {"Agricultural Sciences": 50},
            {"Accounting": 50},
            {"Life Sciences": 50},
            {"Economics": 50},
            {"Geography": 50}
        ],
        "Duration": "4 years"
    },
    {
        "Qualification": "Bachelor of Environmental Sciences in Disaster Risk Reduction",
        "Qualification Code": "ESBDRR",
        "ID": 980,
        "APS": 35,
        "Subject": [
            {"English": 50},
            {"Geography": 60},
            {"Mathematics": 60},
            {"Life Sciences": 60},
            {"Physical Sciences": 50},
            {"Economics": 50}
        ],
        "Duration": "4 Years"
    }
]
