[
    {
        "Institution": "Nelson Mandela University",
        "Code": "BBH1022",
        "Name": "Introduction To Marketing",
        "Description": "TO BE UPDATED",
        "NQF": 5,
        "Credits": 12,
        "Duration":"Term",
        "Period":[3,4],
        "Prerequisite": "TO BE UPDATED",
        "Corequisite": "TO BE UPDATED"
    },
    {
        "Institution": "Nelson Mandela University",
        "Code": "BLG1012",
        "Name": "Introduction To Logistics",
        "Description": "This module aims is to provide a clear understanding and importance of the concepts, tools and applications in the field of Logistics management, as well as to integrate theory with practice.",
        "NQF": 5,
        "Credits": 12,
        "Duration":"Term",
        "Period":[3,4],
        "Prerequisite": "TO BE UPDATED",
        "Corequisite": "TO BE UPDATED"
    },
    {
        "Institution": "Nelson Mandela University",
        "Code": "BMM1001",
        "Name": "Introduction To Management",
        "Description": "TO BE UPDATED",
        "NQF": 5,
        "Credits": 12,
        "Duration":"Term",
        "Period":[1,2],
        "Prerequisite": "TO BE UPDATED",
        "Corequisite": "TO BE UPDATED"
    },
    {
        "Institution": "Nelson Mandela University",
        "Code": "ECO1001",
        "Name": "Introduction To Microeconomics",
        "Description": "TO BE UPDATED",
        "NQF": 5,
        "Credits": 12,
        "Duration":"Term",
        "Period":[1,2],
        "Prerequisite": "TO BE UPDATED",
        "Corequisite": "TO BE UPDATED"
    },
    {
        "Institution": "Nelson Mandela University",
        "Code": "ECO1002",
        "Name": "Introduction To Macroeconomics",
        "Description": "This module aims to develop an understanding of the basic macro-economic principles and how the various macro-economic variables impact on any organisation’s viability and operations.",
        "NQF": 5,
        "Credits": 12,
        "Duration":"Term",
        "Period":[3,4],
        "Prerequisite": "TO BE UPDATED",
        "Corequisite": "TO BE UPDATED"
    },
    {
        "Institution": "Nelson Mandela University",
        "Code": "ITV1001",
        "Name": "End-User Computing",
        "Description": "TO BE UPDATED",
        "NQF": 5,
        "Credits": 12,
        "Duration":"Term",
        "Period":[1,2],
        "Prerequisite": "TO BE UPDATED",
        "Corequisite": "TO BE UPDATED"
    },
    {
        "Institution": "Nelson Mandela University",
        "Code": "LKH1000",
        "Name": "Communication In English A",
        "Description": "This module prepares students to apply their knowledge of communication skills in their practice as Business Managers.",
        "NQF": 5,
        "Credits": 24,
        "Duration":"Term",
        "Period":[1,2,3,4],
        "Prerequisite": "TO BE UPDATED",
        "Corequisite": "TO BE UPDATED"
    },
    {
        "Institution": "Nelson Mandela University",
        "Code": "RBA1002",
        "Name": "Business Accounting",
        "Description": "TO BE UPDATED",
        "NQF": 5,
        "Credits": 12,
        "Duration":"Term",
        "Period":[3,4],
        "Prerequisite": "TO BE UPDATED",
        "Corequisite": "TO BE UPDATED"
    },
    {
        "Institution": "Nelson Mandela University",
        "Code": "TOU1011",
        "Name": "Introduction To Tourism",
        "Description": "TO BE UPDATED",
        "NQF": 5,
        "Credits": 12,
        "Duration":"Term",
        "Period":[1,2],
        "Prerequisite": "TO BE UPDATED",
        "Corequisite": "TO BE UPDATED"
    },
    {
        "Institution": "Nelson Mandela University",
        "Code": "BIC2000",
        "Name": "Purchasing Management II",
        "Description": "This module aims to provide learners with a clear understanding of the various concepts, tools and applications in the field of Purchasing management, as well as to integrate theory with practice.",
        "NQF": 6,
        "Credits": 24,
        "Duration": "Term",
        "Period": [1, 2, 3, 4],
        "Prerequisite": "TO BE UPDATED",
        "Corequisite": "TO BE UPDATED"
    },
    {
        "Institution": "Nelson Mandela University",
        "Code": "BIM2000",
        "Name": "Warehouse Management II",
        "Description": "TO BE UPDATED",
        "NQF": 6,
        "Credits": 24,
        "Duration": "Term",
        "Period": [1, 2, 3, 4],
        "Prerequisite": "TO BE UPDATED",
        "Corequisite": "TO BE UPDATED"
    },
    {
        "Institution": "Nelson Mandela University",
        "Code": "BLG2000",
        "Name": "Logistics II",
        "Description": "This module aims to provide learners with a sound knowledge of the basic principles, underpinnings and terminology relating to the Logistics function in a competitive and multi-disciplinary environment.",
        "NQF": 6,
        "Credits": 24,
        "Duration": "Term",
        "Period": [1, 2, 3, 4],
        "Prerequisite": {"Code":"BLG1012"},
        "Corequisite": "TO BE UPDATED"
    },
    {
        "Institution": "Nelson Mandela University",
        "Code": "EBM2010",
        "Name": "Business Management II",
        "Description": "TO BE UPDATED",
        "NQF": 6,
        "Credits": 24,
        "Duration": "Term",
        "Period": [1, 2, 3, 4],
        "Prerequisite": {"Code":"BMM1001"},
        "Corequisite": "TO BE UPDATED"
    },
    {
        "Institution": "Nelson Mandela University",
        "Code": "JHT1221",
        "Name": "Commercial Law-General Principles Of Contract",
        "Description": "This module aims to adequately equip students with the knowledge to understand and apply the basic theoretical principles of the law of contract in the field of commercial law.",
        "NQF": 6,
        "Credits": 12,
        "Duration": "Term",
        "Period": [1, 2],
        "Prerequisite": "TO BE UPDATED",
        "Corequisite": "TO BE UPDATED"
    },
    {
        "Institution": "Nelson Mandela University",
        "Code": "JHT1222",
        "Name": "Commercial Law- Specific Contracts",
        "Description": "This module aims to adequately equip students with the knowledge to understand and apply the basic theoretical principles relating to specific types of legal contracts in the field of commercial law.",
        "NQF": 6,
        "Credits": 12,
        "Duration": "Term",
        "Period": [3, 4],
        "Prerequisite": {"Code":"JHT1221"},
        "Corequisite": "TO BE UPDATED"
    },
    {
        "Institution": "Nelson Mandela University",
        "Code": "BIC3000",
        "Name": "Purchasing Management III",
        "Description": "TO BE UPDATED",
        "NQF": 7,
        "Credits": 30,
        "Duration": "Term",
        "Period": [1, 2, 3, 4],
        "Prerequisite": {"Code":"BIC2000"},
        "Corequisite": "TO BE UPDATED"
    },
    {
        "Institution": "Nelson Mandela University",
        "Code": "BLG3000",
        "Name": "Logistics III",
        "Description": "TO BE UPDATED",
        "NQF": 7,
        "Credits": 30,
        "Duration": "Term",
        "Period": [1, 2, 3, 4],
        "Prerequisite": {"$and": [{"Code":"BLG2000"},{"Code":"BLG2001"}]},
        "Corequisite": "TO BE UPDATED"
    },
    {
        "Institution": "Nelson Mandela University",
        "Code": "BOM1001",
        "Name": "Operations Management",
        "Description": "This module aims to provide learners with a clear understanding of the concepts, tools and applications in the field of Operations management, as well as to integrate theory with practice.",
        "NQF": 7,
        "Credits": 30,
        "Duration": "Term",
        "Period": [1, 2],
        "Prerequisite": "TO BE UPDATED",
        "Corequisite": "TO BE UPDATED"
    },
    {
        "Institution": "Nelson Mandela University",
        "Code": "EBM3010",
        "Name": "Business Management III",
        "Description": "TO BE UPDATED",
        "NQF": 7,
        "Credits": 30,
        "Duration": "Term",
        "Period": [1, 2, 3, 4],
        "Prerequisite": "TO BE UPDATED",
        "Corequisite": "TO BE UPDATED"
    },
    {
        "Institution": "Nelson Mandela University",
        "Code": "ITVL101",
        "Name": "Computer Literacy",
        "Description": "This module will empower learners to harness the power of ICT by equipping students with the knowledge and skills required to be computer literate.",
        "NQF": 5,
        "Credits": 6,
        "Duration": "Term",
        "Period": [1, 2],
        "Prerequisite": "TO BE UPDATED",
        "Corequisite": "TO BE UPDATED"
    },
    {
        "Institution": "Nelson Mandela University",
        "Code": "JJSV100",
        "Name": "Legal Skills",
        "Description": "To equip students with the skills and competencies required for the study of law and to prepare students for entry into legal practice, into a wide range of other careers, which require the application of law, and for post-graduate studies in law",
        "NQF": 5,
        "Credits": 18,
        "Duration": "Term",
        "Period": [1, 2, 3, 4],
        "Prerequisite": "TO BE UPDATED",
        "Corequisite": "TO BE UPDATED"
    },
    {
        "Institution": "Nelson Mandela University",
        "Code": "JJSV112",
        "Name": "Numeracy Skills",
        "Description": "This module will equip students with the essential calculation skills needed to solve problems and to perform optimally in the face of subject-related challenges in the field of Law.",
        "NQF": 5,
        "Credits": 6,
        "Duration": "Term",
        "Period": [3, 4],
        "Prerequisite": "TO BE UPDATED",
        "Corequisite": "TO BE UPDATED"
    },
    {
        "Institution": "Nelson Mandela University",
        "Code": "JJUV100",
        "Name": "Legal Interpretation",
        "Description": "To facilitate skills and competencies to apply the theories and principles of legal interpretation within the framework of a constitutional state",
        "NQF": 5,
        "Credits": 12,
        "Duration": "Term",
        "Period": [1, 2, 3, 4],
        "Prerequisite": "TO BE UPDATED",
        "Corequisite": "TO BE UPDATED"
    },
    {
        "Institution": "Nelson Mandela University",
        "Code": "JLKV100",
        "Name": "Introduction To Law",
        "Description": "To provide students with a foundational knowledge of the development of the concept of law, the history of South African law, pluralism, and the South African legal framework",
        "NQF": 5,
        "Credits": 24,
        "Duration": "Term",
        "Period": [1, 2, 3, 4],
        "Prerequisite": "TO BE UPDATED",
        "Corequisite": "TO BE UPDATED"
    },
    {
        "Institution": "Nelson Mandela University",
        "Code": "JLPV101",
        "Name": "Law Of Persons",
        "Description": "For students to gain knowledge, skills and competencies to understand the Law of Persons and the Law of Parent and Child",
        "NQF": 5,
        "Credits": 12,
        "Duration": "Term",
        "Period": [1, 2],
        "Prerequisite": "TO BE UPDATED",
        "Corequisite": "TO BE UPDATED"
    },
    {
        "Institution": "Nelson Mandela University",
        "Code": "JLVV102",
        "Name": "Family Law",
        "Description": "For students to gain knowledge, skills and competencies in order to understand Family law",
        "NQF": 5,
        "Credits": 12,
        "Duration": "Term",
        "Period": [3, 4],
        "Prerequisite": "TO BE UPDATED",
        "Corequisite": "TO BE UPDATED"
    },
    {
        "Institution": "Nelson Mandela University",
        "Code": "LELV101",
        "Name": "Academic English (Law)",
        "Description": "This module prepares students to use spoken and written English effectively in legal professions.",
        "NQF": 5,
        "Credits": 12,
        "Duration": "Term",
        "Period": [1, 2],
        "Prerequisite": "TO BE UPDATED",
        "Corequisite": "TO BE UPDATED"
    },
    {
        "Institution": "Nelson Mandela University",
        "Code": "EB121",
        "Name": "Introduction To Business Mngt. & Entrep.",
        "Description": "To equip learners with scientifically-based Business Management knowledge which will enable them to establish, manage and grow their own small business enterprises.",
        "NQF": 5,
        "Credits": 12,
        "Duration": "Term",
        "Period": [1, 2],
        "Prerequisite": "TO BE UPDATED",
        "Corequisite": "TO BE UPDATED"
    },
    {
        "Institution": "Nelson Mandela University",
        "Code": "EB122",
        "Name": "Introduction To The Business Functions",
        "Description": "To equip students with scientifically-based Business Management knowledge which will enable them to establish, manage and grow their own small businesses. This module deals specifically with the business functions.",
        "NQF": 5,
        "Credits": 12,
        "Duration": "Term",
        "Period": [3, 4],
        "Prerequisite": "TO BE UPDATED",
        "Corequisite": "TO BE UPDATED"
    },
    {
        "Institution": "Nelson Mandela University",
        "Code": "ECC101",
        "Name": "Introduction To Micro Economics",
        "Description": "This module will introduce students to the basic concepts of micro-economics. Topics include demand and supply, market equilibrium, elasticity, market structures and market failure.",
        "NQF": 5,
        "Credits": 12,
        "Duration": "Term",
        "Period": [1, 2],
        "Prerequisite": "TO BE UPDATED",
        "Corequisite": "TO BE UPDATED"
    },
    {
        "Institution": "Nelson Mandela University",
        "Code": "ECC102",
        "Name": "Introduction To Macro Economics",
        "Description": "The purpose of this module is to provide students with entry-level foundational economics. This will help them understand the forces within the economy, for example, demand and supply, and it will also prepare them for entry into second-year economics, if they are so inclined.",
        "NQF": 5,
        "Credits": 12,
        "Duration": "Term",
        "Period": [3, 4],
        "Prerequisite": "TO BE UPDATED",
        "Corequisite": "TO BE UPDATED"
    },
    {
        "Institution": "Nelson Mandela University",
        "Code": "FFL101",
        "Name": "Foundations Of French A",
        "Description": "TO BE UPDATED",
        "NQF": 5,
        "Credits": 12,
        "Duration": "Term",
        "Period": [1, 2],
        "Prerequisite": {"Code":"FFL101"},
        "Corequisite": "TO BE UPDATED"
    },
    {
        "Institution": "Nelson Mandela University",
        "Code": "FFL102",
        "Name": "Foundations Of French B",
        "Description": "TO BE UPDATED",
        "NQF": 5,
        "Credits": 12,
        "Duration": "Term",
        "Period": [3, 4],
        "Prerequisite": "FFL101",
        "Corequisite": "TO BE UPDATED"
    },
    {
        "Institution": "Nelson Mandela University",
        "Code": "LEPV101",
        "Name": "Practical English (Eng L2)",
        "Description": "This module equips second-language English students to understand the terminology of basic English grammar and rules of syntax as well as their application at sentence level.",
        "NQF": 5,
        "Credits": 6,
        "Duration": "Term",
        "Period": [1],
        "Prerequisite": "TO BE UPDATED",
        "Corequisite": "TO BE UPDATED"
    },
    {
        "Institution": "Nelson Mandela University",
        "Code": "LEPV111",
        "Name": "Practical English (Eng L2)",
        "Description": "This module equips second-language English students to understand the terminology of basic English grammar and rules of syntax as well as their application at sentence level.",
        "NQF": 5,
        "Credits": 6,
        "Duration": "Term",
        "Period": [2],
        "Prerequisite": "TO BE UPDATED",
        "Corequisite": "TO BE UPDATED"
    },
    {
        "Institution": "Nelson Mandela University",
        "Code": "RNCV111",
        "Name": "Business Accounting 1a",
        "Description": "The module aims to equip students with an understanding of accounting concepts, principles, assumptions, procedures and conventions and to develop skills which enable application of this knowledge in practical circumstances.",
        "NQF": 5,
        "Credits": 12,
        "Duration": "Term",
        "Period": [1, 2],
        "Prerequisite": "TO BE UPDATED",
        "Corequisite": "TO BE UPDATED"
    },
    {
        "Institution": "Nelson Mandela University",
        "Code": "SLCV102",
        "Name": "Introduction To Conflict Management",
        "Description": "This module will provide students with an overview and basic understanding of the role of conflict in society, the most important scholarly approaches and theories, and a general overview of the negotiation process.",
        "NQF": 5,
        "Credits": 6,
        "Duration": "Term",
        "Period": [3],
        "Prerequisite": "TO BE UPDATED",
        "Corequisite": "TO BE UPDATED"
    },
    {
        "Institution": "Nelson Mandela University",
        "Code": "SLP111",
        "Name": "Political Issues,Theories And Concepts",
        "Description": "This module is important since it aims to provide the student with a critical understanding of basic political issues, concepts and theories – creating a foundation upon which the knowledge obtained can be applied in all other political studies modules.",
        "NQF": 5,
        "Credits": 6,
        "Duration": "Term",
        "Period": [1],
        "Prerequisite": "TO BE UPDATED",
        "Corequisite": "TO BE UPDATED"
    },
    {
        "Institution": "Nelson Mandela University",
        "Code": "SLPV111",
        "Name": "Contemporary Sa Politics And Policy",
        "Description": "This module aims to introduce students to political and policy issues in South Africa. Further this module serves to introduce students to theoretical positions within a South African context. This module incorporates political parties, political economy, racial ethnic-gender paradigms and the branches of government. The objective is to inform students that the South African political environment continues to change since 1994. The purpose is to inform students not only of the role of government, but of non-state actors, citizens and the role of the Constitution.",
        "NQF": 5,
        "Credits": 6,
        "Duration": "Term",
        "Period": [2],
        "Prerequisite": "TO BE UPDATED",
        "Corequisite": "TO BE UPDATED"
    },
    {
        "Institution": "Nelson Mandela University",
        "Code": "SLPV112",
        "Name": "Introduction To International Relations",
        "Description": "This module will prepare students to become familiarised with the field of international relations, the broad nature of and dynamics of the current international system and the most important actors on the international stage.",
        "NQF": 5,
        "Credits": 6,
        "Duration": "Term",
        "Period": [4],
        "Prerequisite": "TO BE UPDATED",
        "Corequisite": "TO BE UPDATED"
    },
    {
        "Institution": "Nelson Mandela University",
        "Code": "STAV101",
        "Name": "Financial Mathematics",
        "Description": "The module aims to provide a solid knowledge foundation that covers subject and content knowledge of Time Value of Money and Introductory Operations Research.",
        "NQF": 5,
        "Credits": 12,
        "Duration": "Term",
        "Period": [1, 2],
        "Prerequisite": "TO BE UPDATED",
        "Corequisite": "TO BE UPDATED"
    },
    {
        "Institution": "Nelson Mandela University",
        "Code": "STAV102",
        "Name": "Business Statistics I",
        "Description": "This module provides the student with a sound understanding of the applications of probability and statistics.",
        "NQF": 5,
        "Credits": 12,
        "Duration": "Term",
        "Period": [3, 4],
        "Prerequisite": "TO BE UPDATED",
        "Corequisite": "TO BE UPDATED"
    },
    {
        "Institution": "Nelson Mandela University",
        "Code": "JJCV200",
        "Name": "Criminal Law",
        "Description": "To facilitate the acquisition of knowledge, skills and competencies relating to the general principles of criminal law and specific crimes",
        "NQF": 6,
        "Credits": 18,
        "Duration": "Term",
        "Period": [1, 2, 3, 4],
        "Prerequisite": "TO BE UPDATED",
        "Corequisite": "TO BE UPDATED"
    },
    {
        "Institution": "Nelson Mandela University",
        "Code": "JJHV202",
        "Name": "Human Rights Law",
        "Description": "For students to gain knowledge, skills and competencies to understand the rights entrenched in the Bill of Rights, constitutional values, and the application thereof",
        "NQF": 6,
        "Credits": 12,
        "Duration": "Term",
        "Period": [3, 4],
        "Prerequisite": "TO BE UPDATED",
        "Corequisite": "TO BE UPDATED"
    },
    {
        "Institution": "Nelson Mandela University",
        "Code": "JJTV200",
        "Name": "Constitutional Law",
        "Description": "The purpose of this module is for students to gain knowledge, skills and competencies to understand the Constitution and the functioning of a constitutional state",
        "NQF": 6,
        "Credits": 18,
        "Duration": "Term",
        "Period": [1, 2, 3, 4],
        "Prerequisite": "TO BE UPDATED",
        "Corequisite": "TO BE UPDATED"
    },
    {
        "Institution": "Nelson Mandela University",
        "Code": "JLCV200",
        "Name": "Law Of Contract",
        "Description": "For students to gain knowledge, skills and competencies relating to the general principles of the Law of Contract",
        "NQF": 6,
        "Credits": 24,
        "Duration": "Term",
        "Period": [1, 2, 3, 4],
        "Prerequisite": "TO BE UPDATED",
        "Corequisite": "TO BE UPDATED"
    },
    {
        "Institution": "Nelson Mandela University",
        "Code": "JLJV202",
        "Name": "Private International Law",
        "Description": "For students to gain knowledge, skills and competencies to understand and apply the principles of private international law ",
        "NQF": 6,
        "Credits": 6,
        "Duration": "Term",
        "Period": [3, 4],
        "Prerequisite": "TO BE UPDATED",
        "Corequisite": "TO BE UPDATED"
    },
    {
        "Institution": "Nelson Mandela University",
        "Code": "JLSV201",
        "Name": "Law Of Succession",
        "Description": "For students to gain knowledge, skills and competencies in the Law of Succession",
        "NQF": 6,
        "Credits": 12,
        "Duration": "Term",
        "Period": [1, 2],
        "Prerequisite": "TO BE UPDATED",
        "Corequisite": "TO BE UPDATED"
    },
    {
        "Institution": "Nelson Mandela University",
        "Code": "JLTV211",
        "Name": "Law Of Property",
        "Description": "TO BE UPDATED",
        "NQF": 6,
        "Credits": 12,
        "Duration": "Term",
        "Period": [1, 2],
        "Prerequisite": "TO BE UPDATED",
        "Corequisite": "TO BE UPDATED"
    },
    {
        "Institution": "Nelson Mandela University",
        "Code": "LELV202",
        "Name": "Language And The Law In A Multilingual Societ",
        "Description": "TO BE UPDATED",
        "NQF": 6,
        "Credits": 6,
        "Duration": "Term",
        "Period": [3, 4],
        "Prerequisite": "TO BE UPDATED",
        "Corequisite": "TO BE UPDATED"
    },
    {
        "Institution": "Nelson Mandela University",
        "Code": "JLAV201",
        "Name": "Conversational Afrikaans For Law",
        "Description": "TO BE UPDATED",
        "NQF": 6,
        "Credits": 6,
        "Duration": "Term",
        "Period": [1, 2],
        "Prerequisite": "TO BE UPDATED",
        "Corequisite": "TO BE UPDATED"
    },
    {
        "Institution": "Nelson Mandela University",
        "Code": "JLXV211",
        "Name": "Conversational Isixhosa For Law",
        "Description": "TO BE UPDATED",
        "NQF": 6,
        "Credits": 6,
        "Duration": "Term",
        "Period": [1, 2],
        "Prerequisite": "TO BE UPDATED",
        "Corequisite": "TO BE UPDATED"
    },
    {
        "Institution": "Nelson Mandela University",
        "Code": "JBEV300",
        "Name": "Business Entities Law",
        "Description": "For students to acquire in-depth legal knowledge, skills and competencies to understand and apply the law relating to the various forms of business entities.",
        "NQF": 7,
        "Credits": 24,
        "Duration": "Term",
        "Period": [1, 2, 3, 4],
        "Prerequisite": "TO BE UPDATED",
        "Corequisite": "TO BE UPDATED"
    },
    {
        "Institution": "Nelson Mandela University",
        "Code": "JJBV300",
        "Name": "Civil Procedure",
        "Description": "For students to gain knowledge, skills and competencies relating to civil procedure",
        "NQF": 7,
        "Credits": 12,
        "Duration": "Term",
        "Period": [1, 2, 3, 4],
        "Prerequisite": "TO BE UPDATED",
        "Corequisite": "TO BE UPDATED"
    },
    {
        "Institution": "Nelson Mandela University",
        "Code": "JJEV300",
        "Name": "Law Of Evidence",
        "Description": "For students to gain knowledge, skills and competencies relating to the law of evidence and the practical application thereof",
        "NQF": 7,
        "Credits": 12,
        "Duration": "Term",
        "Period": [1, 2, 3, 4],
        "Prerequisite": "TO BE UPDATED",
        "Corequisite": "TO BE UPDATED"
    },
    {
        "Institution": "Nelson Mandela University",
        "Code": "JJPV300",
        "Name": "Criminal Procedure",
        "Description": "For students to gain knowledge, skills and competencies relating to criminal procedure and the practical application thereof",
        "NQF": 7,
        "Credits": 12,
        "Duration": "Term",
        "Period": [1, 2, 3, 4],
        "Prerequisite": "TO BE UPDATED",
        "Corequisite": "TO BE UPDATED"
    },
    {
        "Institution": "Nelson Mandela University",
        "Code": "JJVV301",
        "Name": "Public International Law",
        "Description": "For students to understand and apply the principles of public international law, and to provide an understanding of the influence of international bodies on inter-state behaviour",
        "NQF": 7,
        "Credits": 12,
        "Duration": "Term",
        "Period": [1, 2],
        "Prerequisite": "TO BE UPDATED",
        "Corequisite": "TO BE UPDATED"
    },
    {
        "Institution": "Nelson Mandela University",
        "Code": "JJVV301",
        "Name": "Public International Law",
        "Description": "For students to understand and apply the principles of public international law, and to provide an understanding of the influence of international bodies on inter-state behaviour",
        "NQF": 7,
        "Credits": 12,
        "Duration": "Term",
        "Period": [3, 4],
        "Prerequisite": "TO BE UPDATED",
        "Corequisite": "TO BE UPDATED"
    },
    {
        "Institution": "Nelson Mandela University",
        "Code": "JLDV300",
        "Name": "Law Of Delict",
        "Description": "To facilitate the acquisition of knowledge and practical skills relating to the general principles of the law of delict and delictual damages",
        "NQF": 7,
        "Credits": 24,
        "Duration": "Term",
        "Period": [1, 2, 3, 4],
        "Prerequisite": "TO BE UPDATED",
        "Corequisite": "TO BE UPDATED"
    },
    {
        "Institution": "Nelson Mandela University",
        "Code": "JLQV302",
        "Name": "Law Of Sale And Lease",
        "Description": "To provide students with the knowledge, skills and competencies of the law relating to the contracts of sale and lease",
        "NQF": 7,
        "Credits": 12,
        "Duration": "Term",
        "Period": [3, 4],
        "Prerequisite": "TO BE UPDATED",
        "Corequisite": "TO BE UPDATED"
    },
    {
        "Institution": "Nelson Mandela University",
        "Code": "JLXV300",
        "Name": "African Customary Law",
        "Description": "To equip students with knowledge, skills and competencies of aspects of African Customary Law and an appreciation for values and principles of this field of law within its historical and constitutional context",
        "NQF": 7,
        "Credits": 12,
        "Duration": "Term",
        "Period": [1, 2, 3, 4],
        "Prerequisite": "TO BE UPDATED",
        "Corequisite": "TO BE UPDATED"
    },
    {
        "Institution": "Nelson Mandela University",
        "Code": "JMLV300",
        "Name": "Labour Law",
        "Description": "To provide students with the knowledge, skills and competencies regarding individual employment law, collective labour law, social insurance law and the applicable labour-dispute resolution bodies and processes",
        "NQF": 7,
        "Credits": 12,
        "Duration": "Term",
        "Period": [1, 2, 3, 4],
        "Prerequisite": "TO BE UPDATED",
        "Corequisite": "TO BE UPDATED"
    },
    {
        "Institution": "Nelson Mandela University",
        "Code": "JARL412",
        "Name": "Law And Regional Integration In Africa",
        "Description": "To provide students with the knowledge, skills and competencies regarding individual employment law, collective labour law, social insurance law and the applicable labour-dispute resolution bodies and processes",
        "NQF": 8,
        "Credits": 12,
        "Duration": "Term",
        "Period": [3, 4],
        "Prerequisite": {"Code":"JJVV301"},
        "Corequisite": "TO BE UPDATED"
    },
    {
        "Institution": "Nelson Mandela University",
        "Code": "JCLV402",
        "Name": "Consumer Protection And Credit Law",
        "Description": "TO BE UPDATED",
        "NQF": 8,
        "Credits": 12,
        "Duration": "Term",
        "Period": [3, 4],
        "Prerequisite": {"Code":"JLCV200"},
        "Corequisite": "TO BE UPDATED"
    },
    {
        "Institution": "Nelson Mandela University",
        "Code": "JILB401",
        "Name": "Insolvency, Liquidation And Business Rescue",
        "Description": "TO BE UPDATED",
        "NQF": 8,
        "Credits": 12,
        "Duration": "Term",
        "Period": [1, 2],
        "Prerequisite": "TO BE UPDATED",
        "Corequisite": "TO BE UPDATED"
    },
    {
        "Institution": "Nelson Mandela University",
        "Code": "JJAV401",
        "Name": "Administrative Law",
        "Description": "For students to gain knowledge, skills and competencies to understand and apply the law governing administrative power and functions",
        "NQF": 8,
        "Credits": 12,
        "Duration": "Term",
        "Period": [1, 2],
        "Prerequisite": "JJTV200",
        "Corequisite": "TO BE UPDATED"
    },
    {
        "Institution": "Nelson Mandela University",
        "Code": "JJJV402",
        "Name": "Jurisprudence",
        "Description": "This module will prepare students to encounter, understand and apply numerous jurisprudential theories which address, from diverse perspectives, the nature and critique of law and the legal system.",
        "NQF": 8,
        "Credits": 12,
        "Duration": "Term",
        "Period": [3, 4],
        "Prerequisite": "TO BE UPDATED",
        "Corequisite": "TO BE UPDATED"
    },
    {
        "Institution": "Nelson Mandela University",
        "Code": "JJWV400",
        "Name": "Legal Practice",
        "Description": "For students to gain knowledge, skills and competencies relating to legal practice",
        "NQF": 8,
        "Credits": 12,
        "Duration": "Term",
        "Period": [1, 2, 3, 4],
        "Prerequisite": "TO BE UPDATED",
        "Corequisite": "TO BE UPDATED"
    },
    {
        "Institution": "Nelson Mandela University",
        "Code": "JMCV401",
        "Name": "Ict Law",
        "Description": "To equip students with comprehensive knowledge of, and insight into the legal aspects of information and communication technology (ICT)",
        "NQF": 8,
        "Credits": 12,
        "Duration": "Term",
        "Period": [1, 2],
        "Prerequisite": "TO BE UPDATED",
        "Corequisite": "TO BE UPDATED"
    },
    {
        "Institution": "Nelson Mandela University",
        "Code": "JAPL402",
        "Name": "Advanced Private Law- Capita Selecta",
        "Description": "To gain knowledge, skills and competencies relating to the law of Unjustified Enrichment, law of Estoppel, and law of Cession, Assignment and Delegation and the application thereof",
        "NQF": 8,
        "Credits": 12,
        "Duration": "Term",
        "Period": [3, 4],
        "Prerequisite": "TO BE UPDATED",
        "Corequisite": "TO BE UPDATED"
    },
    {
        "Institution": "Nelson Mandela University",
        "Code": "JCYV400",
        "Name": "Legal Research Assignments (Criminal Law)",
        "Description": "To facilitate the acquisition of knowledge, skills and competencies pertaining to legal research methodology for drafting a legal research assignment",
        "NQF": 8,
        "Credits": 12,
        "Duration": "Term",
        "Period": [1, 2, 3, 4],
        "Prerequisite": "TO BE UPDATED",
        "Corequisite": "TO BE UPDATED"
    },
    {
        "Institution": "Nelson Mandela University",
        "Code": "JCZV400",
        "Name": "Llb Treatise (Criminal Law)",
        "Description": "TO BE UPDATED",
        "NQF": 8,
        "Credits": 24,
        "Duration": "Term",
        "Period": [1, 2, 3, 4],
        "Prerequisite": "TO BE UPDATED",
        "Corequisite": "TO BE UPDATED"
    },
    {
        "Institution": "Nelson Mandela University",
        "Code": "JFLV402",
        "Name": "Forensic Legal Evidence",
        "Description": "For students to gain knowledge, skills and competencies to understand the principles and technologies of forensic science used in the detection and investigation of crimes, and in the presentation of evidence to address legal issues in criminal proceedings",
        "NQF": 8,
        "Credits": 12,
        "Duration": "Term",
        "Period": [3, 4],
        "Prerequisite": "JJEV300",
        "Corequisite": "TO BE UPDATED"
    },
    {
        "Institution": "Nelson Mandela University",
        "Code": "JJCV411",
        "Name": "Advanced Criminal And Procedural Law",
        "Description": "TO BE UPDATED",
        "NQF": 8,
        "Credits": 12,
        "Duration": "Term",
        "Period": [1, 2],
        "Prerequisite": "JJCV200",
        "Corequisite": "TO BE UPDATED"
    },
    {
        "Institution": "Nelson Mandela University",
        "Code": "JJDV401",
        "Name": "Moot Court",
        "Description": "To facilitate the acquisition of mooting skills and competencies",
        "NQF": 8,
        "Credits": 12,
        "Duration": "Term",
        "Period": [1, 2],
        "Prerequisite": "TO BE UPDATED",
        "Corequisite": "TO BE UPDATED"
    },
    {
        "Institution": "Nelson Mandela University",
        "Code": "JJIV401",
        "Name": "International Humanitarian Law",
        "Description": "To provide adequate knowledge relating to international humanitarian law in light of past and contemporary armed conflicts.",
        "NQF": 8,
        "Credits": 12,
        "Duration": "Term",
        "Period": [1, 2],
        "Prerequisite": "JJVV301",
        "Corequisite": "TO BE UPDATED"
    },
    {
        "Institution": "Nelson Mandela University",
        "Code": "JJNV402",
        "Name": "Environmental Law",
        "Description": "For students to gain knowledge, skills and competencies to understand and apply the foundations of environmental law",
        "NQF": 8,
        "Credits": 12,
        "Duration": "Term",
        "Period": [3, 4],
        "Prerequisite": "TO BE UPDATED",
        "Corequisite": "TO BE UPDATED"
    },
    {
        "Institution": "Nelson Mandela University",
        "Code": "JJXV401",
        "Name": "Law Of The Sea",
        "Description": "To facilitate the acquisition of knowledge and practical skills relating to the legal aspects of human activities at sea",
        "NQF": 8,
        "Credits": 12,
        "Duration": "Term",
        "Period": [1, 2],
        "Prerequisite": "TO BE UPDATED",
        "Corequisite": "TO BE UPDATED"
    },
    {
        "Institution": "Nelson Mandela University",
        "Code": "JJYV400",
        "Name": "Legal Research Assignments (Public Law)",
        "Description": "TO BE UPDATED",
        "NQF": 8,
        "Credits": 12,
        "Duration": "Term",
        "Period": [1, 2, 3, 4],
        "Prerequisite": "TO BE UPDATED",
        "Corequisite": "TO BE UPDATED"
    },
    {
        "Institution": "Nelson Mandela University",
        "Code": "JJZV400",
        "Name": "Llb Treatise (Public Law)",
        "Description": "TO BE UPDATED",
        "NQF": 8,
        "Credits": 24,
        "Duration": "Term",
        "Period": [1, 2, 3, 4],
        "Prerequisite": "TO BE UPDATED",
        "Corequisite": "TO BE UPDATED"
    },
    {
        "Institution": "Nelson Mandela University",
        "Code": "JLFV402",
        "Name": "Advanced Family Law",
        "Description": "TO BE UPDATED",
        "NQF": 8,
        "Credits": 12,
        "Duration": "Term",
        "Period": [3, 4],
        "Prerequisite": {"Code":"JLVV102"},
        "Corequisite": "TO BE UPDATED"
    },
    {
        "Institution": "Nelson Mandela University",
        "Code": "JLYV400",
        "Name": "Legal Research Assignments (Private Law)",
        "Description": "TO BE UPDATED",
        "NQF": 8,
        "Credits": 12,
        "Duration": "Term",
        "Period": [1, 2, 3, 4],
        "Prerequisite": "TO BE UPDATED",
        "Corequisite": "TO BE UPDATED"
    },
    {
        "Institution": "Nelson Mandela University",
        "Code": "JLZV400",
        "Name": "Llb Treatise (Private Law)",
        "Description": "TO BE UPDATED",
        "NQF": 8,
        "Credits": 24,
        "Duration": "Term",
        "Period": [1, 2, 3, 4],
        "Prerequisite": "TO BE UPDATED",
        "Corequisite": "TO BE UPDATED"
    },
    {
        "Institution": "Nelson Mandela University",
        "Code": "JMHV401",
        "Name": "Law Of International Trade",
        "Description": "TO BE UPDATED",
        "NQF": 8,
        "Credits": 12,
        "Duration": "Term",
        "Period": [1, 2],
        "Prerequisite": "TO BE UPDATED",
        "Corequisite": "TO BE UPDATED"
    },
    {
        "Institution": "Nelson Mandela University",
        "Code": "JMRV401",
        "Name": "Intellectual Property Law",
        "Description": "To facilitate the acquisition of knowledge relating to the legal aspects of Intellectual Property Law",
        "NQF": 8,
        "Credits": 12,
        "Duration": "Term",
        "Period": [1, 2],
        "Prerequisite": "TO BE UPDATED",
        "Corequisite": "TO BE UPDATED"
    },
    {
        "Institution": "Nelson Mandela University",
        "Code": "JMRV402",
        "Name": "Competition Law",
        "Description": "To gain knowledge, skills and competencies to understand and apply competition legislation and the principles of public and private competition law",
        "NQF": 8,
        "Credits": 12,
        "Duration": "Term",
        "Period": [3, 4],
        "Prerequisite": "TO BE UPDATED",
        "Corequisite": "TO BE UPDATED"
    },
    {
        "Institution": "Nelson Mandela University",
        "Code": "JMTV400",
        "Name": "Law Of Taxation",
        "Description": "To provide students with knowledge, skills and competencies in relation to income tax, value added tax, estate duty, transfer duty and tax administration laws",
        "NQF": 8,
        "Credits": 12,
        "Duration": "Term",
        "Period": [1, 2, 3, 4],
        "Prerequisite": "TO BE UPDATED",
        "Corequisite": "TO BE UPDATED"
    },
    {
        "Institution": "Nelson Mandela University",
        "Code": "JMYV400",
        "Name": "Legal Research Assignments (Mercantile Law)",
        "Description": "TO BE UPDATED",
        "NQF": 8,
        "Credits": 12,
        "Duration": "Term",
        "Period": [1, 2, 3, 4],
        "Prerequisite": "TO BE UPDATED",
        "Corequisite": "TO BE UPDATED"
    },
    {
        "Institution": "Nelson Mandela University",
        "Code": "JMZV400",
        "Name": "Llb Treatise (Mercantile Law)",
        "Description": "TO BE UPDATED",
        "NQF": 8,
        "Credits": 24,
        "Duration": "Term",
        "Period": [1, 2, 3, 4],
        "Prerequisite": "TO BE UPDATED",
        "Corequisite": "TO BE UPDATED"
    },
    {
        "Institution": "Nelson Mandela University",
        "Code": "JPLV401",
        "Name": "Advanced Property Law",
        "Description": "To facilitate the acquisition of knowledge of the fundamental legal principles relating to property development schemes, the law of agency, land tenure, eviction law and the eviction of occupiers",
        "NQF": 8,
        "Credits": 12,
        "Duration": "Term",
        "Period": [3, 4],
        "Prerequisite": "JLTV211",
        "Corequisite": "TO BE UPDATED"
    },
    {
        "Institution": "Nelson Mandela University",
        "Code": "JRLV402",
        "Name": "Refugee Law",
        "Description": "TO BE UPDATED",
        "NQF": 8,
        "Credits": 12,
        "Duration": "Term",
        "Period": [3, 4],
        "Prerequisite": "TO BE UPDATED",
        "Corequisite": "TO BE UPDATED"
    },
    {
        "Institution": "Nelson Mandela University",
        "Code": "RPV102",
        "Name": "Accounting 1p",
        "Description": "This is the second module introducing students to financial accounting and has been designed primarily for law students. This module provides students with the knowledge and skills in financial accounting which will equip them to pass the bookkeeping for attorneys section of the Attorney’s admission examination.",
        "NQF": 5,
        "Credits": 10,
        "Duration": "Term",
        "Period": [3, 4],
        "Prerequisite": "RPV111",
        "Corequisite": "TO BE UPDATED"
    },
    {
        "Institution": "Nelson Mandela University",
        "Code": "RPV111",
        "Name": "Business Accounting 1a",
        "Description": "TO BE UPDATED",
        "NQF": 5,
        "Credits": 12,
        "Duration": "Term",
        "Period": [1, 2],
        "Prerequisite": "TO BE UPDATED",
        "Corequisite": "TO BE UPDATED"
    }
]




