[{
    "Qualification": "Diploma in Adult and Community Education and Training",
    "ID": 833890437,
    "Qualification Code": "W62001",
    "APS": 21,
    "Description": "To prepare students to become reflective and competent lecturers in Community Colleges. It articulates vertically to teacher education programmes pitching at NQF level 7.",
    "Entrance": [
        "AND",
        {
            "subjectid": 103,
            "minmark": 40,
            "required": true
        },
        ["OR",
        {"subjectid": 56, "minmark": 40, "required": true},
        {"subjectid": 45, "minmark": 40, "required": true}
        ],
        [
            "OR",
            {
                "subjectid": 2,
                "minmark": 30,
                "required": true
            },
            {
                "subjectid": 21,
                "minmark": 30,
                "required": true
            }
        ]
    ]
},
{
    "Qualification": "Bachelor of Education in Foundation Phase Teaching",
    "ID": 469634872,
    "Qualification Code": "W62006",
    "APS": 26,
    "Description": "This is an initial professional teacher qualification with specialization linked to Grades R – 3. It provides specific depth and specialised knowledge, practical skills through research and workplace experience to enable successful students to enter teaching well grounded.",
    "Subject": [
        "AND",
        {
            "subjectid": 103,
            "minmark": 50,
            "required": true
        },
        ["OR",
        {"subjectid": 56, "minmark": 50, "required": true},
        {"subjectid": 45, "minmark": 50, "required": true}
        ],
        {
            "subjectid": 4,
            "minmark": 60,
            "required": true
        },
        [
            "OR",
            {
                "subjectid": 2,
                "minmark": 30,
                "required": true
            },
            {
                "subjectid": 21,
                "minmark": 50,
                "required": true
            }
        ]
    ]
},
{
    "Qualification": "Bachelor of Education in Senior Phase and Further Education and Training Teaching (Economic & Management Sciences)",
    "ID": 1574,
    "Qualification Code": "W62009",
    "APS": 26,
    "Description": "The primary purpose of the Bachelor of Education in Senior Phase and Further Education and Training Teaching (SP & FET) is to provide a well-rounded education that equips graduates with the required subject content knowledge base, educational theory, and methodology that will enable them to demonstrate competence and responsibility as academically and professionally qualified beginner teachers.",
    "Subject": [
        "AND",
        {
            "subjectid": 103,
            "minmark": 50,
            "required": true
        },
        ["OR",
        {"subjectid": 56, "minmark": 40, "required": true},
        {"subjectid": 45, "minmark": 40, "required": true}
        ],
        [
            "ANY2",
            {
                "subjectid": 7,
                "minmark": 50,
                "required": true
            },
            {
                "subjectid": 26,
                "minmark": 50,
                "required": true
            },
            {
                "subjectid": 27,
                "minmark": 50,
                "required": true
            }
        ],
        [
            "OR",
            {
                "subjectid": 2,
                "minmark": 30,
                "required": true
            },
            {
                "subjectid": 21,
                "minmark": 50,
                "required": true
            }
        ]
    ]
},
{
    "Qualification": "Bachelor of Education in Senior Phase and Further Education and Training Teaching (Consumer and Management Sciences)",
    "ID": 5420,
    "Qualification Code": "W62008",
    "APS": 23,
    "Description": "The primary purpose of the Bachelor of Education in Senior Phase and Further Education and Training Teaching (SP & FET) is to provide a well-rounded education that equips graduates with the required subject content knowledge base, educational theory, and methodology that will enable them to demonstrate competence and responsibility as academically and professionally qualified beginner teachers.",
    "Subject": [
        "AND",
        {
            "subjectid": 103,
            "minmark": 50,
            "required": true
        },
        {
            "subjectid": 28,
            "minmark": 50,
            "required": true
        },
        [
            "OR",
            {
                "subjectid": 29,
                "minmark": 50,
                "required": true
            },
            {
                "subjectid": 30,
                "minmark": 50,
                "required": true
            }
        ],
        ["OR",
        {"subjectid": 97, "minmark": 50, "required": true},
        {"subjectid": 96, "minmark": 50, "required": true}
        ]
    ]
},
{
    "Qualification": "Bachelor of Education in Senior Phase and Further Education and Training (Creative Arts)",
    "ID": 5422,
    "Qualification Code": "W62007",
    "APS": 26,
    "Description": "The primary purpose of the Bachelor of Education in Senior Phase and Further Education and Training Teaching (SP & FET) is to provide a well-rounded education that equips graduates with the required subject content knowledge base, educational theory, and methodology that will enable them to demonstrate competence and responsibility as academically and professionally qualified beginner teachers.",
    "Subject": [
        "AND",
        {
            "subjectid": 103,
            "minmark": 50,
            "required": true
        },
        {
            "subjectid": 34,
            "minmark": 50,
            "required": true
        },
        ["OR",
        {"subjectid": 97, "minmark": 50, "required": true},
        {"subjectid": 96, "minmark": 50, "required": true}
        ],
        [
            "ANY2",
            {
                "subjectid": 33,
                "minmark": 50,
                "required": true
            },
            {
                "subjectid": 35,
                "minmark": 50,
                "required": true
            },
            {
                "subjectid": 31,
                "minmark": 50,
                "required": true
            },
            {
                "subjectid": 24,
                "minmark": 50,
                "required": true
            },
            {
                "subjectid": 4,
                "minmark": 50,
                "required": true
            }
        ]
    ]
},
{
    "Qualification": "Bachelor of Education in Senior Phase and Further Education and Training Teaching (Humanities)",
    "ID": 5418,
    "Qualification Code": "W62010",
    "APS": 26,
    "Description": "The primary purpose of the Bachelor of Education in Senior Phase and Further Education and Training Teaching (SP & FET) is to provide a well-rounded education that equips graduates with the required subject content knowledge base, educational theory, and methodology that will enable them to demonstrate competence and responsibility as academically and professionally qualified beginner teachers.",
    "Subject": [
        "AND",
        {
            "subjectid": 103,
            "minmark": 50,
            "required": true
        },
        ["OR",
        {"subjectid": 97, "minmark": 50, "required": true},
        {"subjectid": 96, "minmark": 50, "required": true}
        ],
        {
            "subjectid": 24,
            "minmark": 50,
            "required": true
        },
        {
            "subjectid": 8,
            "minmark": 50,
            "required": true
        },
        {
            "subjectid": 4,
            "minmark": 50,
            "required": true
        }
    ]
},
{
    "Qualification": "Bachelor of Education in Senior Phase and Further Education and Training Teaching (Languages)",
    "ID": 601184927,
    "Qualification Code": "W62011",
    "APS": 26,
    "Description": "The primary purpose of the Bachelor of Education in Senior Phase and Further Education and Training Teaching (SP & FET) is to provide a well-rounded education that equips graduates with the required subject content knowledge base, educational theory, and methodology that will enable them to demonstrate competence and responsibility as academically and professionally qualified beginner teachers.",
    "Subject": [
        "AND",
        {
            "subjectid": 103,
            "minmark": 60,
            "required": true
        },
        ["OR",
        {"subjectid": 97, "minmark": 50, "required": true},
        {"subjectid": 96, "minmark": 50, "required": true}
        ],
        {
            "subjectid": 4,
            "minmark": 50,
            "required": true
        }
    ]
},
{
    "Qualification": "Bachelor of Education in Senior Phase and Further Education and Training Teaching (Mathematics, Science & Technology)",
    "ID": 5421,
    "Qualification Code": "W62012",
    "APS": 26,
    "Description": "The primary purpose of the Bachelor of Education in Senior Phase and Further Education and Training Teaching (SP & FET) is to provide a well-rounded education that equips graduates with the required subject content knowledge base, educational theory, and methodology that will enable them to demonstrate competence and responsibility as academically and professionally qualified beginner teachers.",
    "Subject": [
        "AND",
        {
            "subjectid": 103,
            "minmark": 50,
            "required": true
        },
        ["OR",
        {"subjectid": 97, "minmark": 50, "required": true},
        {"subjectid": 96, "minmark": 50, "required": true}
        ],
        [
            "ANY2",
            {
                "subjectid": 19,
                "minmark": 50,
                "required": true
            },
            {
                "subjectid": 2,
                "minmark": 50,
                "required": true
            },
            {
                "subjectid": 20,
                "minmark": 50,
                "required": true
            }
        ]
    ]
},
{
    "Qualification": "Bachelor of Education in Senior Phase and Further Education and Training Teaching (Technical and Vocational)",
    "ID": 62018,
    "Qualification Code": "W62018",
    "APS": 0,
    "Description": "The degree is a 480-credit qualification, offered over a period of 4 years, full-time. Students need to study 3 modules/courses as Majors: Major A (the main FET Major with content and teaching up to Level III), Major B (the second FET Major with content and teaching up to Level II), and Major C (the third Senior Phase Major with content and teaching up to Level II). Options include combinations like Civil Technology and Engineering Graphics & Design; Electrical Technology, Engineering Graphics & Design, and Technology; Mechanical Technology, Engineering Graphics & Design, and Technology; and others with Technology (SP) as a compulsory subject studied up to Level II.",
    "Subject": [
        "AND",
        {
            "subjectid": 103,
            "minmark": 50,
            "required": true
        },
        [
            "ANY2",
            {
                "subjectid": 115,
                "minmark": 40,
                "required": true
            },
            {
                "subjectid": 2,
                "minmark": 40,
                "required": true
            },
            {
                "subjectid": 114,
                "minmark": 40,
                "required": true
            },
            {
                "subjectid": 20,
                "minmark": 40,
                "required": true
            },
            {
                "subjectid": 38,
                "minmark": 40,
                "required": true
            },
            {
                "subjectid": 36,
                "minmark": 40,
                "required": true
            },
            {
                "subjectid": 37,
                "minmark": 40,
                "required": true
            },
            {
                "subjectid": 39,
                "minmark": 40,
                "required": true 
            }
        ],
        ["OR",
        {"subjectid": 97, "minmark": 50, "required": true},
        {"subjectid": 96, "minmark": 50, "required": true}
        ]
    ]
}











]
